[
  {
    "ContainingType": "AgendaContatos.Controllers.ContatosController",
    "Method": "GetContatos",
    "RelativePath": "api/Contatos",
    "HttpMethod": "GET",
    "IsController": true,
    "Order": 0,
    "Parameters": [],
    "ReturnTypes": [
      {
        "Type": "System.Collections.Generic.IEnumerable\u00601[[AgendaContatos.Models.Contato, AgendaContatos, Version=1.0.0.0, Culture=neutral, PublicKeyToken=null]]",
        "MediaTypes": [
          "text/plain",
          "application/json",
          "text/json"
        ],
        "StatusCode": 200
      }
    ]
  },
  {
    "ContainingType": "AgendaContatos.Controllers.ContatosController",
    "Method": "PostContato",
    "RelativePath": "api/Contatos",
    "HttpMethod": "POST",
    "IsController": true,
    "Order": 0,
    "Parameters": [
      {
        "Name": "dto",
        "Type": "AgendaContatos.DTOs.ContatoCreateDTO",
        "IsRequired": true
      }
    ],
    "ReturnTypes": [
      {
        "Type": "AgendaContatos.Models.Contato",
        "MediaTypes": [
          "text/plain",
          "application/json",
          "text/json"
        ],
        "StatusCode": 200
      }
    ]
  },
  {
    "ContainingType": "AgendaContatos.Controllers.ContatosController",
    "Method": "GetContato",
    "RelativePath": "api/Contatos/{id}",
    "HttpMethod": "GET",
    "IsController": true,
    "Order": 0,
    "Parameters": [
      {
        "Name": "id",
        "Type": "System.Int32",
        "IsRequired": true
      }
    ],
    "ReturnTypes": [
      {
        "Type": "AgendaContatos.Models.Contato",
        "MediaTypes": [
          "text/plain",
          "application/json",
          "text/json"
        ],
        "StatusCode": 200
      }
    ]
  },
  {
    "ContainingType": "AgendaContatos.Controllers.ContatosController",
    "Method": "PutContato",
    "RelativePath": "api/Contatos/{id}",
    "HttpMethod": "PUT",
    "IsController": true,
    "Order": 0,
    "Parameters": [
      {
        "Name": "id",
        "Type": "System.Int32",
        "IsRequired": true
      },
      {
        "Name": "dto",
        "Type": "AgendaContatos.DTOs.ContatoCreateDTO",
        "IsRequired": true
      }
    ],
    "ReturnTypes": []
  },
  {
    "ContainingType": "AgendaContatos.Controllers.ContatosController",
    "Method": "DeleteContato",
    "RelativePath": "api/Contatos/{id}",
    "HttpMethod": "DELETE",
    "IsController": true,
    "Order": 0,
    "Parameters": [
      {
        "Name": "id",
        "Type": "System.Int32",
        "IsRequired": true
      }
    ],
    "ReturnTypes": []
  },
  {
    "ContainingType": "AgendaContatos.Controllers.ContatosController",
    "Method": "ListarBackups",
    "RelativePath": "api/Contatos/backup",
    "HttpMethod": "GET",
    "IsController": true,
    "Order": 0,
    "Parameters": [],
    "ReturnTypes": []
  }
]